quest/__init__.py
quest/client.py
quest/context.py
quest/custom_exceptions.py
quest/external.py
quest/extras/__init__.py
quest/extras/aws.py
quest/extras/sql.py
quest/historian.py
quest/history.py
quest/lifecycle.py
quest/manager.py
quest/manager_wrappers.py
quest/persistence.py
quest/quest_types.py
quest/resources.py
quest/serializer.py
quest/server.py
quest/utils.py
quest/versioning.py
quest/wrappers.py
quest_py-0.2.16.dist-info/METADATA
quest_py-0.2.16.dist-info/WHEEL
quest_py-0.2.16.dist-info/RECORD
