Metadata-Version: 2.4
Name: quest.py
Version: 0.2.16
Summary: Framework for coordinated, long-running processes
Author: Gordon Bean
Author-email: gbean@cs.byu.edu
Requires-Python: >=3.11,<4.0
Classifier: Programming Language :: Python :: 3
Classifier: Programming Language :: Python :: 3.11
Classifier: Programming Language :: Python :: 3.12
Classifier: Programming Language :: Python :: 3.13
Classifier: Programming Language :: Python :: 3.14
Provides-Extra: aws
Provides-Extra: server
Provides-Extra: sql
